coupang/__init__.py
coupang/category.py
coupang/common.py
coupang/cs.py
coupang/exchange.py
coupang/ordersheet.py
coupang/product.py
coupang/return.py
coupang/returns.py
coupang/search.py
coupang/settlement.py
coupang/shipping.py
coupang-1.4.2.dist-info/METADATA
coupang-1.4.2.dist-info/WHEEL
coupang-1.4.2.dist-info/top_level.txt
coupang-1.4.2.dist-info/RECORD
